Gtdata/Gt.py
Gtdata/__init__.py
Gtdata-0.0.1.dist-info/LICENSE
Gtdata-0.0.1.dist-info/METADATA
Gtdata-0.0.1.dist-info/WHEEL
Gtdata-0.0.1.dist-info/top_level.txt
Gtdata-0.0.1.dist-info/RECORD
