Metadata-Version: 2.1
Name: Gtdata
Version: 0.0.1
Summary: GtdataPR
Home-page: https://github.com/pypa/sampleproject
Author: Sail
Author-email: yusail333@gmail.com
License: UNKNOWN
Project-URL: Bug Tracker, https://github.com/pypa/sampleproject/issues
Platform: UNKNOWN
Classifier: Programming Language :: Python :: 3
Classifier: License :: OSI Approved :: MIT License
Classifier: Operating System :: OS Independent
Requires-Python: >=3.6
License-File: LICENSE
